CONTRIBUTING.rst
CONTRIBUTORS.rst
HISTORY.rst
LICENSE
README.rst
docs/Makefile
docs/background.rst
docs/conf.py
docs/contributing.rst
docs/contributors.rst
docs/history.rst
docs/index.rst
docs/installation.rst
docs/make.bat
docs/readme.rst
docs/reference.rst
docs/usage.rst
jointly/__init__.py
jointly/abstract_extractor.py
jointly/helpers.py
jointly/helpers_plotting.py
jointly/log.py
jointly/shake_extractor.py
jointly/synchronization_errors.py
jointly/synchronizer.py
jointly/types.py
tests/parquet_reader.py
tests/test_examples.py
tests/test_helpers.py
tests/test_helpers_plotting.py
tests/test_shake_extractor.py
tests/test_synchronizer.py
jointly-1.0.4.dist-info/LICENSE
jointly-1.0.4.dist-info/WHEEL
jointly-1.0.4.dist-info/METADATA
jointly-1.0.4.dist-info/RECORD
