Metadata-Version: 2.1
Name: jointly
Version: 1.0.4
Summary: Synchronize sensor data from accelerometer shakes
Home-page: https://github.com/hpi-dhc/jointly
License: MIT
Author: Ariane Morassi Sasso
Author-email: ariane.morassi-sasso@hpi.de
Requires-Python: >=3.7.1,<3.10
Classifier: License :: OSI Approved :: MIT License
Classifier: Programming Language :: Python
Classifier: Programming Language :: Python :: 3
Classifier: Programming Language :: Python :: 3.7
Classifier: Programming Language :: Python :: 3.8
Classifier: Programming Language :: Python :: 3.9
Requires-Dist: matplotlib (>=3.4.2,<4.0.0)
Requires-Dist: numpy (>=1.21.1,<2.0.0)
Requires-Dist: pandas (>=1.3.1,<2.0.0)
Requires-Dist: scipy (>=1.7.1,<2.0.0)
Project-URL: Documentation, https://hpi-dhc.github.io/jointly
Project-URL: Repository, https://github.com/hpi-dhc/jointly
